mind/__init__.py
mind/config.py
mind/container.py
mind/adapters/__init__.py
mind/adapters/standard/__init__.py
mind/adapters/standard/apscheduler_runner.py
mind/adapters/standard/pgvector_search.py
mind/adapters/standard/postgres_causal.py
mind/adapters/standard/postgres_events.py
mind/adapters/standard/postgres_storage.py
mind/adapters/testing/__init__.py
mind/adapters/testing/stubs.py
mind/api/__init__.py
mind/api/app.py
mind/api/deps.py
mind/api/routes/__init__.py
mind/api/routes/admin.py
mind/api/routes/causal.py
mind/api/routes/consent.py
mind/api/routes/decisions.py
mind/api/routes/health.py
mind/api/routes/interactions.py
mind/api/routes/memories.py
mind/api/routes/metrics.py
mind/api/routes/preferences.py
mind/api/schemas/__init__.py
mind/api/schemas/causal.py
mind/api/schemas/consent.py
mind/api/schemas/decision.py
mind/api/schemas/interaction.py
mind/api/schemas/memory.py
mind/api/schemas/preferences.py
mind/cli/__init__.py
mind/cli/demo.py
mind/cli/health.py
mind/cli/migrate.py
mind/cli/serve.py
mind/cli/setup.py
mind/cli/version.py
mind/cli/worker.py
mind/core/__init__.py
mind/core/errors.py
mind/core/causal/__init__.py
mind/core/causal/dowhy_integration.py
mind/core/causal/models.py
mind/core/causal/service.py
mind/core/causal/shapley.py
mind/core/consent/__init__.py
mind/core/consent/models.py
mind/core/consent/service.py
mind/core/decision/__init__.py
mind/core/decision/models.py
mind/core/events/__init__.py
mind/core/events/base.py
mind/core/events/decision.py
mind/core/events/interaction.py
mind/core/events/memory.py
mind/core/federation/__init__.py
mind/core/federation/effectiveness.py
mind/core/federation/extractor.py
mind/core/federation/models.py
mind/core/federation/sanitizer.py
mind/core/federation/service.py
mind/core/memory/__init__.py
mind/core/memory/fusion.py
mind/core/memory/models.py
mind/core/memory/retrieval.py
mind/core/retention/__init__.py
mind/core/retention/models.py
mind/core/retention/service.py
mind/dashboard/__init__.py
vibeship_mind-5.0.1.dist-info/METADATA
vibeship_mind-5.0.1.dist-info/WHEEL
vibeship_mind-5.0.1.dist-info/entry_points.txt
vibeship_mind-5.0.1.dist-info/licenses/LICENSE
vibeship_mind-5.0.1.dist-info/RECORD
