Metadata-Version: 2.4
Name: vibeship-mind
Version: 5.0.1
Summary: Decision intelligence system for AI agents - hierarchical memory with outcome-weighted retrieval
Project-URL: Homepage, https://github.com/vibeship/vibeship-mind
Project-URL: Documentation, https://github.com/vibeship/vibeship-mind#readme
Project-URL: Repository, https://github.com/vibeship/vibeship-mind
Project-URL: Issues, https://github.com/vibeship/vibeship-mind/issues
Author-email: Vibeship <hello@vibeship.com>
License: MIT
License-File: LICENSE
Keywords: agents,ai,claude,decisions,llm,memory,pgvector
Classifier: Development Status :: 4 - Beta
Classifier: Intended Audience :: Developers
Classifier: License :: OSI Approved :: MIT License
Classifier: Programming Language :: Python :: 3.12
Classifier: Topic :: Scientific/Engineering :: Artificial Intelligence
Requires-Python: >=3.12
Requires-Dist: aiohttp>=3.9.0
Requires-Dist: alembic>=1.13.0
Requires-Dist: apscheduler>=3.10.0
Requires-Dist: asyncpg>=0.29.0
Requires-Dist: certifi>=2024.0.0
Requires-Dist: cryptography>=41.0.0
Requires-Dist: falkordb>=1.0.0
Requires-Dist: fastapi>=0.109.0
Requires-Dist: httpx>=0.26.0
Requires-Dist: mcp>=1.0.0
Requires-Dist: nats-py>=2.6.0
Requires-Dist: opentelemetry-api>=1.22.0
Requires-Dist: opentelemetry-instrumentation-fastapi>=0.43b0
Requires-Dist: opentelemetry-sdk>=1.22.0
Requires-Dist: orjson>=3.9.0
Requires-Dist: pgvector>=0.2.4
Requires-Dist: prometheus-client>=0.19.0
Requires-Dist: pydantic-settings>=2.1.0
Requires-Dist: pydantic>=2.5.0
Requires-Dist: pyjwt>=2.8.0
Requires-Dist: python-ulid>=2.2.0
Requires-Dist: sqlalchemy[asyncio]>=2.0.25
Requires-Dist: structlog>=24.1.0
Requires-Dist: temporalio>=1.4.0
Requires-Dist: uvicorn[standard]>=0.27.0
Provides-Extra: dev
Requires-Dist: httpx>=0.26.0; extra == 'dev'
Requires-Dist: mypy>=1.8.0; extra == 'dev'
Requires-Dist: pytest-asyncio>=0.23.0; extra == 'dev'
Requires-Dist: pytest-cov>=4.1.0; extra == 'dev'
Requires-Dist: pytest>=8.0.0; extra == 'dev'
Requires-Dist: ruff>=0.1.14; extra == 'dev'
Requires-Dist: testcontainers[nats,postgres]>=3.7.0; extra == 'dev'
Provides-Extra: ml
Requires-Dist: dowhy>=0.11.0; extra == 'ml'
Requires-Dist: econml>=0.15.0; extra == 'ml'
Requires-Dist: numpy>=1.26.0; extra == 'ml'
Requires-Dist: openai>=1.12.0; extra == 'ml'
Requires-Dist: sentence-transformers>=2.2.0; extra == 'ml'
Provides-Extra: ui
Requires-Dist: pandas>=2.1.0; extra == 'ui'
Requires-Dist: plotly>=5.18.0; extra == 'ui'
Requires-Dist: streamlit>=1.29.0; extra == 'ui'
Provides-Extra: vector
Requires-Dist: qdrant-client>=1.7.0; extra == 'vector'
